tests/__init__.py
tests/ewt.py
tests/run.py
tests/utils.py
web3tools/__init__.py
web3tools/ewt.py
web3tools/providers.py
web3tools/reader.py
web3tools/transactor.py
web3tools/utils.py
web3tools-0.1.2.dist-info/LICENSE
web3tools-0.1.2.dist-info/METADATA
web3tools-0.1.2.dist-info/WHEEL
web3tools-0.1.2.dist-info/top_level.txt
web3tools-0.1.2.dist-info/RECORD
