Metadata-Version: 2.1
Name: web3tools
Version: 0.1.2
Summary: Web3Py Extender Tools
Home-page: https://github.com/zepcp/web3tools
Author: José Pereira
Author-email: zepcp@hotmail.com
License: UNKNOWN
Platform: UNKNOWN
Classifier: Programming Language :: Python :: 3
Classifier: License :: OSI Approved :: MIT License
Classifier: Operating System :: OS Independent
Requires-Python: >=3.7
License-File: LICENSE
